{
    "asset": {
        "format": "jpg",
        "id": "22e3f84b0e64f1953a0c722545860252",
        "name": "pedro-da-silva-unEmGQqdO7Q-unsplash.jpg",
        "path": "file:C:/src/MLNetHelpers/ObjectDetectionTutorial/data/images/stop-signs/pedro-da-silva-unEmGQqdO7Q-unsplash.jpg",
        "size": {
            "width": 2271,
            "height": 2271
        },
        "state": 2,
        "type": 1
    },
    "regions": [
        {
            "id": "TCw1OLdsco",
            "type": "POLYGON",
            "tags": [
                "Stop-Sign"
            ],
            "boundingBox": {
                "height": 637.6339501206758,
                "width": 495.1255028157683,
                "left": 902.5534995977474,
                "top": 1386.716814159292
            },
            "points": [
                {
                    "x": 1251.5164923572004,
                    "y": 1386.716814159292
                },
                {
                    "x": 1043.234915526951,
                    "y": 1399.5060337892196
                },
                {
                    "x": 911.688656476267,
                    "y": 1585.8632341110217
                },
                {
                    "x": 902.5534995977474,
                    "y": 1837.9935639581656
                },
                {
                    "x": 1034.0997586484311,
                    "y": 2024.3507642799677
                },
                {
                    "x": 1238.7272727272727,
                    "y": 2002.4263877715205
                },
                {
                    "x": 1394.0249396621077,
                    "y": 1819.7232502011263
                },
                {
                    "x": 1397.6790024135157,
                    "y": 1551.1496379726468
                },
                {
                    "x": 1255.1705551086081,
                    "y": 1390.3708769107
                }
            ]
        }
    ],
    "version": "2.2.0"
}